datalake_ftp/__init__.py
datalake_ftp/cli.py
datalake_ftp-1.0.1.dist-info/entry_points.txt
datalake_ftp-1.0.1.dist-info/LICENSE
datalake_ftp-1.0.1.dist-info/WHEEL
datalake_ftp-1.0.1.dist-info/METADATA
datalake_ftp-1.0.1.dist-info/RECORD
