Metadata-Version: 2.1
Name: datalake-ftp
Version: 1.0.1
Summary: Moves files from FTP drop folders to a Cloud Bucket
Home-page: https://git.equancy.cloud/equancy/data-technologies/datalake-ftp
License: MIT
Author: Didier SCHMITT
Author-email: dschmitt@equancy.com
Requires-Python: >=3.8,<4.0
Classifier: License :: OSI Approved :: MIT License
Classifier: Programming Language :: Python :: 3
Classifier: Programming Language :: Python :: 3.10
Classifier: Programming Language :: Python :: 3.8
Classifier: Programming Language :: Python :: 3.9
Requires-Dist: PyYAML (>=6.0,<7.0)
Requires-Dist: click (>=8.0.3,<9.0.0)
Requires-Dist: datalake-framework (>=1.0.2,<2.0.0)
Requires-Dist: pendulum (>=2.1.2,<3.0.0)
Project-URL: Repository, https://git.equancy.cloud/equancy/data-technologies/datalake-ftp
